{
    "Bedford Esquires": {
        "date": "05/09/2025"
    },
    "Fiddler's Elbow": {
        "date": "03/09/2025"
    },
    "Stag's Head": {
        "date": "16/08/2025"
    },
    "Southwark Tavern": {
        "date": "12/07/2025"
    },
    "Black Heart": {
        "date": "28/06/2025"
    },
    "Claddagh Ring": {
        "date": "13/06/2025"
    },
    "Old Queen's Head": {
        "date": "05/06/2025"
    },
    "Spice of Life": {
        "date": "16/05/2025"
    },
    "Fiddler's Elbow": {
        "date": "30/04/2025"
    },
    "Trinity Bar": {
        "date": "25/01/2025"
    },
    "Trinity Bar": {
        "date": "02/11/2024"
    },
    "Good Mixer": {
        "date": "26/09/2024"
    },
    "Walthamstow Trades Hall": {
        "date": "20/09/2024"
    },
    "Orford House": {
        "date": "24/08/2024"
    }
}